Metadata-Version: 2.1
Name: sphinx-docslab
Version: 0.1.0
Summary: Sphinx docslab extension for interactive code
Author-email: "rerobots, Inc." <q@rerobots.net>
License: Apache-2.0
Project-URL: source, https://github.com/rerobots/docslab
Classifier: License :: OSI Approved :: Apache Software License
Classifier: Development Status :: 4 - Beta
Requires-Python: >=3.9
Requires-Dist: sphinx
